logfire_mcp/__init__.py
logfire_mcp/__main__.py
mseep_logfire_mcp-1.0.0.dist-info/licenses/LICENSE
mseep_logfire_mcp-1.0.0.dist-info/METADATA
mseep_logfire_mcp-1.0.0.dist-info/WHEEL
mseep_logfire_mcp-1.0.0.dist-info/top_level.txt
mseep_logfire_mcp-1.0.0.dist-info/RECORD
